loglito/__init__.py
loglito/client.py
loglito-0.1.32.dist-info/licenses/LICENSE
loglito-0.1.32.dist-info/METADATA
loglito-0.1.32.dist-info/WHEEL
loglito-0.1.32.dist-info/top_level.txt
loglito-0.1.32.dist-info/RECORD
